Cdriver/DriverChecker.py
Cdriver/EnvRefer.py
Cdriver/__init__.py
Cdriver/chromePath.ini
Cdriver/bean/Deploy.py
Cdriver/bean/__init__.py
Cdriver/common/__init__.py
Cdriver/common/readConfig.py
Cdriver-0.0.6.data/scripts/chromePath.ini
Cdriver-0.0.6.dist-info/METADATA
Cdriver-0.0.6.dist-info/WHEEL
Cdriver-0.0.6.dist-info/top_level.txt
Cdriver-0.0.6.dist-info/RECORD
