Metadata-Version: 2.1
Name: Cdriver
Version: 0.0.6
Summary: Automatically download the browser drivers
Home-page: https://github.com/BarryYBL/Cdriver
Author: Barry
Author-email: YBL2652612315@126.com
License: BSD
Platform: UNKNOWN
Classifier: Intended Audience :: Developers
Classifier: Operating System :: MacOS :: MacOS X
Classifier: Operating System :: Microsoft :: Windows
Classifier: Programming Language :: Python
Classifier: Programming Language :: Python :: 3.5
Classifier: Programming Language :: Python :: 3.6
Classifier: Programming Language :: Python :: 3.7
Classifier: Topic :: Internet :: WWW/HTTP :: Dynamic Content
Classifier: Topic :: Software Development :: Testing
Requires-Dist: certifi (==2020.12.5)
Requires-Dist: chardet (==4.0.0)
Requires-Dist: idna (==2.10)
Requires-Dist: requests (==2.25.1)
Requires-Dist: urllib3 (==1.26.2)
